README.md
setup.py
hn_sum/__init__.py
hn_sum.egg-info/PKG-INFO
hn_sum.egg-info/SOURCES.txt
hn_sum.egg-info/dependency_links.txt
hn_sum.egg-info/entry_points.txt
hn_sum.egg-info/requires.txt
hn_sum.egg-info/top_level.txt